src/__init__.py
src/agent.py
src/client.py
src/exceptions.py
src/session.py
src/tool.py
src/tools.py
src/types.py
poping-0.1.1.dist-info/METADATA
poping-0.1.1.dist-info/WHEEL
poping-0.1.1.dist-info/top_level.txt
poping-0.1.1.dist-info/RECORD
