Metadata-Version: 2.4
Name: poping
Version: 0.1.1
Summary: Poping AI Agent SDK
Author: Poping
Requires-Python: >=3.10
Requires-Dist: requests>=2.31.0
Dynamic: author
Dynamic: requires-dist
Dynamic: requires-python
Dynamic: summary
